<?xml version="1.0"?>
<!DOCTYPE liferay-portlet-app PUBLIC "-//Liferay//DTD Portlet Application 6.2.0//EN" "http://www.liferay.com/dtd/liferay-portlet-app_6_2_0.dtd">
<liferay-portlet-app>
	
	<portlet>
		<portlet-name>home-page-portlet</portlet-name>
		<icon>/icon.png</icon>
		<header-portlet-css>/css/main.css</header-portlet-css>
		<footer-portlet-javascript>/js/home-page-portlet.js</footer-portlet-javascript>
		<css-class-wrapper>home-page-portlet</css-class-wrapper>
	</portlet>
	
	<portlet>
		<portlet-name>classificazione-portlet1</portlet-name>
		<icon>/icon.png</icon>
		<header-portlet-css>/css/main.css</header-portlet-css>
		<footer-portlet-javascript>/js/classificazione-portlet1.js</footer-portlet-javascript>
		<css-class-wrapper>classificazione-portlet1</css-class-wrapper>
	</portlet>
	
	<portlet>
		<portlet-name>testata-navigazione-portlet</portlet-name>
		<icon>/icon.png</icon>
		<header-portlet-css>/css/main.css</header-portlet-css>
		<footer-portlet-javascript>/js/testata-navigazione-portlet.js</footer-portlet-javascript>
		<css-class-wrapper>testata-navigazione-portlet</css-class-wrapper>
	</portlet>
	
	<portlet>
		<portlet-name>pie-chart-portlet</portlet-name>
		<icon>/icon.png</icon>
		<requires-namespaced-parameters>false</requires-namespaced-parameters>
		<header-portlet-css>/css/main.css</header-portlet-css>
		<footer-portlet-javascript>/js/pie-chart-portlet.js</footer-portlet-javascript>
		<css-class-wrapper>pie-chart-portlet</css-class-wrapper>
	</portlet>
	
	<portlet>
		<portlet-name>soggetto-portlet</portlet-name>
		<icon>/icon.png</icon>
		<requires-namespaced-parameters>false</requires-namespaced-parameters>
		<header-portlet-css>/css/main.css</header-portlet-css>
		<footer-portlet-javascript>/js/soggetto-portlet.js</footer-portlet-javascript>
		<css-class-wrapper>soggetto-portlet</css-class-wrapper>
	</portlet>
	
	<portlet>
		<portlet-name>natura-portlet1</portlet-name>
		<icon>/icon.png</icon>
		<header-portlet-css>/css/main.css</header-portlet-css>
		<footer-portlet-javascript>/js/natura-portlet1.js</footer-portlet-javascript>
		<css-class-wrapper>natura-portlet1</css-class-wrapper>
	</portlet>
	
	<portlet>
		<portlet-name>natura-portlet2</portlet-name>
		<icon>/icon.png</icon>
		<header-portlet-css>/css/main.css</header-portlet-css>
		<footer-portlet-javascript>/js/natura-portlet2.js</footer-portlet-javascript>
		<css-class-wrapper>natura-portlet2</css-class-wrapper>
	</portlet>
	
	<portlet>
		<portlet-name>natura-portlet3</portlet-name>
		<icon>/icon.png</icon>
		<header-portlet-css>/css/main.css</header-portlet-css>
		<footer-portlet-javascript>/js/natura-portlet3.js</footer-portlet-javascript>
		<css-class-wrapper>natura-portlet3</css-class-wrapper>
	</portlet>
	
	<portlet>
		<portlet-name>natura-portlet-ricerca</portlet-name>
		<icon>/icon.png</icon>
		<header-portlet-css>/css/main.css</header-portlet-css>
		<footer-portlet-javascript>/js/natura-portlet-ricerca.js</footer-portlet-javascript>
		<css-class-wrapper>natura-portlet-ricerca</css-class-wrapper>
	</portlet>
	
	<portlet>
		<portlet-name>elenco-progetti-portlet</portlet-name>
		<icon>/icon.png</icon>
		<footer-portlet-css>/css/main.css</footer-portlet-css>
		<footer-portlet-javascript>/js/elenco-progetti-portlet.js</footer-portlet-javascript>
		<css-class-wrapper>elenco-progetti-portlet</css-class-wrapper>
	</portlet>
	
	<portlet>
		<portlet-name>dettaglio-progetto-portlet</portlet-name>
		<icon>/icon.png</icon>
		<footer-portlet-css>/css/main.css</footer-portlet-css>
		<footer-portlet-javascript>/js/dettaglio-progetto-portlet.js</footer-portlet-javascript>
		<css-class-wrapper>dettaglio-progetto-portlet</css-class-wrapper>
	</portlet>
	
	<portlet>
		<portlet-name>localizzazione-portlet</portlet-name>
		<icon>/icon.png</icon>
		<header-portlet-css>/css/main.css</header-portlet-css>
		<footer-portlet-javascript>/js/localizzazione-portlet.js</footer-portlet-javascript>
		<css-class-wrapper>localizzazione-portlet</css-class-wrapper>
	</portlet>
	
	<portlet>
		<portlet-name>localizzazione-portlet0</portlet-name>
		<icon>/icon.png</icon>
		<header-portlet-css>/css/main.css</header-portlet-css>
		<footer-portlet-javascript>/js/localizzazione-portlet0.js</footer-portlet-javascript>
		<css-class-wrapper>localizzazione-portlet0</css-class-wrapper>
	</portlet>
	
	<portlet>
		<portlet-name>localizzazione-portlet1</portlet-name>
		<icon>/icon.png</icon>
		<header-portlet-css>/css/main.css</header-portlet-css>
		<footer-portlet-javascript>/js/localizzazione-portlet1.js</footer-portlet-javascript>
		<css-class-wrapper>localizzazione-portlet1</css-class-wrapper>
	</portlet>
	
	<portlet>
		<portlet-name>localizzazione-portlet2</portlet-name>
		<icon>/icon.png</icon>
		<header-portlet-css>/css/main.css</header-portlet-css>
		<footer-portlet-javascript>/js/localizzazione-portlet2.js</footer-portlet-javascript>
		<css-class-wrapper>localizzazione-portlet2</css-class-wrapper>
	</portlet>
	
	<portlet>
		<portlet-name>localizzazione-portlet3</portlet-name>
		<icon>/icon.png</icon>
		<header-portlet-css>/css/main.css</header-portlet-css>
		<footer-portlet-javascript>/js/localizzazione-portlet3.js</footer-portlet-javascript>
		<css-class-wrapper>localizzazione-portlet3</css-class-wrapper>
	</portlet>
	
	<portlet>
		<portlet-name>localizzazione-portlet4</portlet-name>
		<icon>/icon.png</icon>
		<header-portlet-css>/css/main.css</header-portlet-css>
		<footer-portlet-javascript>/js/localizzazione-portlet4.js</footer-portlet-javascript>
		<css-class-wrapper>localizzazione-portlet3</css-class-wrapper>
	</portlet>
	
	<portlet>
		<portlet-name>ricercalibera-portlet</portlet-name>
		<icon>/icon.png</icon>
		<indexer-class>it.dipe.opencup.utils.ProgettoIndexer</indexer-class>
		<header-portlet-css>/css/main.css</header-portlet-css>
		<footer-portlet-javascript>/js/ricercalibera-portlet.js</footer-portlet-javascript>
		<css-class-wrapper>ricercalibera-portlet</css-class-wrapper>
		<add-default-resource>true</add-default-resource>
		
	</portlet>
	
	<portlet>
		<portlet-name>ricerca-configurazione-portlet</portlet-name>
		<icon>/icon.png</icon>
		<control-panel-entry-category>site_administration.content</control-panel-entry-category>
		<control-panel-entry-weight>1.5</control-panel-entry-weight>
		<header-portlet-css>/css/main.css</header-portlet-css>
		<footer-portlet-javascript>/js/ricerca-configurazione-portlet.js</footer-portlet-javascript>
		<css-class-wrapper>ricercarisultati-portlet</css-class-wrapper>
		<add-default-resource>true</add-default-resource>
	</portlet>
	
	<portlet>
		<portlet-name>contattaci-portlet</portlet-name>
		<icon>/icon.png</icon>
		<header-portlet-css>/css/main.css</header-portlet-css>
		<footer-portlet-javascript>/js/contattaci-portlet.js</footer-portlet-javascript>
		<css-class-wrapper>contattaci-portlet</css-class-wrapper>
	</portlet>
	
	
	<role-mapper>
		<role-name>administrator</role-name>
		<role-link>Administrator</role-link>
	</role-mapper>
	<role-mapper>
		<role-name>guest</role-name>
		<role-link>Guest</role-link>
	</role-mapper>
	<role-mapper>
		<role-name>power-user</role-name>
		<role-link>Power User</role-link>
	</role-mapper>
	<role-mapper>
		<role-name>user</role-name>
		<role-link>User</role-link>
	</role-mapper>
</liferay-portlet-app>